{
  "auth": {
    "chatapp2a973b5c": {
      "service": "Cognito",
      "providerPlugin": "awscloudformation",
      "dependsOn": [],
      "customAuth": false
    },
    "userPoolGroups": {
      "service": "Cognito-UserPool-Groups",
      "providerPlugin": "awscloudformation",
      "dependsOn": [
        {
          "category": "auth",
          "resourceName": "chatapp2a973b5c",
          "attributes": [
            "UserPoolId",
            "AppClientIDWeb",
            "AppClientID",
            "IdentityPoolId"
          ]
        }
      ]
    }
  }
}